rocmi/__init__.py
rocmi/cli.py
rocmi/kfd.py
rocmi-0.3.1.dist-info/LICENSE
rocmi-0.3.1.dist-info/METADATA
rocmi-0.3.1.dist-info/WHEEL
rocmi-0.3.1.dist-info/entry_points.txt
rocmi-0.3.1.dist-info/top_level.txt
rocmi-0.3.1.dist-info/RECORD
