Metadata-Version: 2.1
Name: rocmi
Version: 0.3.1
Summary: Pure Python implementation of ROCm metircs and management interfaces
Home-page: https://github.com/mrodden/rocmi
Author: Mathew Odden
Author-email: matodden@amd.com
License: UNKNOWN
Platform: UNKNOWN
Classifier: License :: OSI Approved :: Apache Software License
Classifier: Programming Language :: Python :: 3
Requires-Python: >=3.6
Provides-Extra: cli
Requires-Dist: prettytable (>=2) ; extra == 'cli'
